[
  {
    "name": "Distance",
    "canonical": "Math.abs(a - b)",
    "answer": "Math.abs(a-b)",
    "correct": true,
    "timestamp": 1661895730807
  },
  {
    "name": "Manhattan distance",
    "canonical": "Math.abs(x1 - x2) + Math.abs(y1 - y2)",
    "answer": "Math.abs(x1-x2)+Math.abs(y1+y2)",
    "correct": false,
    "timestamp": 1661895754930
  },
  {
    "name": "Manhattan distance",
    "canonical": "Math.abs(x1 - x2) + Math.abs(y1 - y2)",
    "answer": "Math.abs(x1-x2)+Math.abs(y1-y2)",
    "correct": true,
    "timestamp": 1661895775107
  },
  {
    "name": "Average",
    "canonical": "(a + b) / 2",
    "answer": "(a+b)/2",
    "correct": true,
    "timestamp": 1661895783138
  },
  {
    "name": "Difference",
    "canonical": "a - b",
    "answer": "a-b",
    "correct": true,
    "timestamp": 1661895795426
  },
  {
    "name": "Seconds in a day",
    "canonical": "24 * 60 * 60",
    "answer": "60*60*24",
    "correct": true,
    "timestamp": 1661895808314
  },
  {
    "name": "Remainder",
    "canonical": "a % b",
    "answer": "a%b",
    "correct": true,
    "timestamp": 1661895812916
  },
  {
    "name": "Area of circle with radius 2",
    "canonical": "Math.PI * 4",
    "answer": "Math.PI*2**2",
    "correct": true,
    "timestamp": 1661895821186
  },
  {
    "name": "Sum",
    "canonical": "a + b",
    "answer": "a+b",
    "correct": true,
    "timestamp": 1661895824091
  },
  {
    "name": "Ratio",
    "canonical": "a / b",
    "answer": "a/b",
    "correct": true,
    "timestamp": 1661895827892
  },
  {
    "name": "1337 times 32",
    "canonical": "1337 * 32",
    "answer": "1337*32",
    "correct": true,
    "timestamp": 1661895851147
  },
  {
    "name": "Sally's even more apples",
    "canonical": "6432 - 4000",
    "answer": "6432-4000",
    "correct": true,
    "timestamp": 1661895860139
  },
  {
    "name": "Product",
    "canonical": "a * b",
    "answer": "a*b",
    "correct": true,
    "timestamp": 1661895863476
  }
]