[
  {
    "name": "Will we skip our trip to the store?",
    "answer": "!storeOpen || linesTooLong",
    "correct": true,
    "timestamp": 1661550822803
  },
  {
    "name": "Wait for a sale?",
    "answer": "!storeOpen ||! isASale",
    "correct": true,
    "timestamp": 1661550832755
  },
  {
    "name": "Coming to bookclub?",
    "answer": "member &&! outSick",
    "correct": true,
    "timestamp": 1661550840139
  },
  {
    "name": "Ready for some football?",
    "answer": "fast && strong",
    "correct": true,
    "timestamp": 1661550846052
  },
  {
    "name": "Lighting a fire?",
    "answer": "!haveMatches || firelit",
    "correct": false,
    "timestamp": 1661550854156
  }
]